{
  "version": "0.3.3",
  "flags": {},
  "shapes": [
    {
      "label": "doc_title",
      "text": "ทะเบียนใบอนุญาตทำงานของคนต่างด้าวตามมติคณะรัฐมนตรี",
      "points": [
        [
          288.66666666666674,
          72.22222222222221
        ],
        [
          1105.3333333333333,
          127.77777777777777
        ]
      ],
      "group_id": null,
      "shape_type": "rectangle",
      "flags": {}
    },
    {
      "label": "foreign_id",
      "text": "0074015961196",
      "points": [
        [
          445.3333333333334,
          653.3333333333334
        ],
        [
          613.1111111111112,
          686.6666666666666
        ]
      ],
      "group_id": null,
      "shape_type": "rectangle",
      "flags": {}
    },
    {
      "label": "cert_id",
      "text": "7400654066445",
      "points": [
        [
          1066.4444444444443,
          650.0
        ],
        [
          1242.0,
          687.7777777777777
        ]
      ],
      "group_id": null,
      "shape_type": "rectangle",
      "flags": {}
    },
    {
      "label": "thai_name",
      "text": "นาย วาย ออง",
      "points": [
        [
          447.55555555555566,
          696.6666666666666
        ],
        [
          576.4444444444446,
          722.2222222222222
        ]
      ],
      "group_id": null,
      "shape_type": "rectangle",
      "flags": {}
    },
    {
      "label": "passport_id",
      "text": "MH087855",
      "points": [
        [
          443.1111111111112,
          954.4444444444445
        ],
        [
          564.2222222222223,
          981.1111111111111
        ]
      ],
      "group_id": null,
      "shape_type": "rectangle",
      "flags": {}
    },
    {
      "label": "employer_name",
      "text": "บริษัท ทริปเปิล พี โปรดักส์ จำกัด",
      "points": [
        [
          440.88888888888897,
          1262.2222222222222
        ],
        [
          739.7777777777778,
          1297.7777777777778
        ]
      ],
      "group_id": null,
      "shape_type": "rectangle",
      "flags": {}
    },
    {
      "label": "expire_date",
      "text": "13 กุมภาพันธ์ 2567",
      "points": [
        [
          1065.3333333333333,
          1576.6666666666665
        ],
        [
          1255.3333333333333,
          1614.4444444444443
        ]
      ],
      "group_id": null,
      "shape_type": "rectangle",
      "flags": {}
    }
  ],
  "imagePath": "VW2400098_permit50_2.png",
  "imageData": null,
  "imageHeight": 2338,
  "imageWidth": 1654
}